{
	"$bog_bhelper_app_crm_Col_city": "Город",
	"$bog_bhelper_app_crm_Col_last_contact": "Последний контакт",
	"$bog_bhelper_app_crm_Col_manager": "Менеджер",
	"$bog_bhelper_app_crm_Col_name": "Клиент",
	"$bog_bhelper_app_crm_Col_next_action": "Следующий шаг",
	"$bog_bhelper_app_crm_Col_segment": "Сегмент",
	"$bog_bhelper_app_crm_Col_status": "Статус",
	"$bog_bhelper_app_crm_ManagerFilter_hint": "Менеджер",
	"$bog_bhelper_app_crm_Search_hint": "Поиск по имени, компании или тегам",
	"$bog_bhelper_app_crm_SegmentFilter_hint": "Сегмент",
	"$bog_bhelper_app_crm_StatusFilter_hint": "Статус",
	"$bog_bhelper_app_crm_add_label": "Новый клиент",
	"$bog_bhelper_app_crm_next_label": "Вперёд",
	"$bog_bhelper_app_crm_prev_label": "Назад",
	"$bog_bhelper_app_crm_reset_label": "Сбросить",
	"$bog_bhelper_app_crm_subtitle_label": "База клиентов малого бизнеса",
	"$bog_bhelper_app_crm_title": "CRM",
	"$bog_bhelper_app_crm_title_label": "Клиенты",
	"$bog_bhelper_app_menu_title": "VibeHelpers",
	"$bog_bhelper_app_prof_Search_hint": "Найти помощника",
	"$bog_bhelper_app_prof_title": "Помощники",
	"$bog_bhelper_app_settings_Install_button_title": "Добавить на главный экран",
	"$bog_bhelper_app_settings_Install_labeler_title": "Установить приложение",
	"$bog_bhelper_app_settings_Language_labeler_title": "Язык интерфейса",
	"$bog_bhelper_app_settings_install_already_installed": "Приложение уже установлено или установка не поддерживается.",
	"$bog_bhelper_app_settings_install_android_instruction": "В Chrome на Android откройте меню (⋮) и выберите \"Установить приложение\".",
	"$bog_bhelper_app_settings_install_desktop_instruction": "На компьютере используйте кнопку установки в адресной строке или пункт меню браузера \"Установить приложение\".",
	"$bog_bhelper_app_settings_install_ios_instruction": "Чтобы добавить на главный экран на iPhone или iPad, нажмите \"Поделиться\" и выберите \"Добавить на главный экран\".",
	"$bog_bhelper_app_settings_install_unsupported_browser": "Добавление на главный экран не поддерживается в этом браузере.",
	"$bog_bhelper_app_settings_title": "Настройки",
	"$bog_bhelper_app_vaka_Credits_title": "Данные предоставлены HeadHunter API",
	"$bog_bhelper_app_vaka_Query_hint": "Поисковый запрос",
	"$bog_bhelper_app_vaka_Search_hint": "Найти",
	"$bog_bhelper_app_vaka_title": "Вакансии HH.ru",
	"$bog_lk_Basics_heading_text": "Основная информация",
	"$bog_lk_Bio_field_name": "О себе",
	"$bog_lk_Bio_input_hint": "Текст о себе",
	"$bog_lk_City_field_name": "Город",
	"$bog_lk_City_input_hint": "Введите город",
	"$bog_lk_Contacts_heading_text": "Контакты",
	"$bog_lk_Country_field_name": "Страна",
	"$bog_lk_Country_input_hint": "Введите страну",
	"$bog_lk_Email_field_name": "Email",
	"$bog_lk_Email_input_hint": "Введите email",
	"$bog_lk_Form_title_text": "Расскажите о себе",
	"$bog_lk_Full_name_field_name": "Полное имя",
	"$bog_lk_Full_name_input_hint": "Укажите полное имя",
	"$bog_lk_Github_field_name": "GitHub",
	"$bog_lk_Github_input_hint": "Ссылка на GitHub",
	"$bog_lk_Location_heading_text": "Локация",
	"$bog_lk_Nickname_field_name": "Имя пользователя",
	"$bog_lk_Nickname_input_hint": "Введите имя пользователя",
	"$bog_lk_Peer_label_text": "ID пользователя",
	"$bog_lk_Share_copy_text_text": "Скопировать",
	"$bog_lk_Share_copy_title": "Скопировать ссылку",
	"$bog_lk_Share_field_hint": "Ссылка на профиль",
	"$bog_lk_Share_title_text": "Поделиться:",
	"$bog_lk_Telegram_field_name": "Telegram",
	"$bog_lk_Telegram_input_hint": "Ссылка на Telegram",
	"$bog_lk_Twitter_field_name": "Twitter",
	"$bog_lk_Twitter_input_hint": "Ссылка на Twitter",
	"$bog_lk_Website_field_name": "Сайт",
	"$bog_lk_Website_input_hint": "Ссылка на сайт",
	"$bog_lk_title": "Личная страница",
	"$bog_theme_picker_Search_hint": "Начните вводить",
	"$bog_theme_toggle_Anchor_hint": "Переключить темы",
	"$gd_bot_Context_title": "Сводка",
	"$gd_bot_Prompt_submit_hint": "Отправить",
	"$gd_bot_Prompt_text_hint": "Спросите что-нибудь",
	"$gd_bot_Reset_hint": "Сбросить",
	"$gd_bot_dialog_title": "Гипер Бот",
	"$mol_book2_catalog_Spread_close_hint": "Закрыть страницу",
	"$mol_form_form_invalid": "Форма заполнена некорректно",
	"$mol_form_message_done": "Сохранено",
	"$mol_form_submit_title": "Сохранить",
	"$mol_lights_toggle_hint": "Переключить тему",
	"$mol_link_donate_hint": "Поблагодарить долларом",
	"$mol_link_source_hint": "Исходный код",
	"$mol_link_support_hint": "Обсудить проект",
	"$mol_search_Clear_hint": "Очистить",
	"$mol_search_hint": "Поиск...",
	"$mol_select_filter_hint": "Фильтр...",
	"$mol_select_hint": "Выбрать...",
	"$mol_select_no_options_message": "Нет вариантов",
	"$mol_text_code_Copy_hint": "Скопировать весь код",
	"$mol_text_header_Link_hint": "Постоянная ссылка на этот раздел"
}
